LICENSE
MANIFEST.in
README.md
setup.py
scripts/BigphASEtools
src/BigphASE/__init__.py
src/BigphASE/maker.py
src/BigphASE/options.py
src/BigphASE/utils.py
src/BigphASE.egg-info/PKG-INFO
src/BigphASE.egg-info/SOURCES.txt
src/BigphASE.egg-info/dependency_links.txt
src/BigphASE.egg-info/top_level.txt
src/BigphASE/delta2hap/CMakeLists.txt
src/BigphASE/delta2hap/bin/delta2hap
src/BigphASE/delta2hap/include/delta.h
src/BigphASE/delta2hap/include/redirect_to_pager.h
src/BigphASE/delta2hap/include/show-vcf.h
src/BigphASE/delta2hap/include/sw_alignscore.h
src/BigphASE/delta2hap/include/tigrinc.h
src/BigphASE/delta2hap/include/translate.h
src/BigphASE/delta2hap/src/delta.cpp
src/BigphASE/delta2hap/src/delta2hap.cpp
src/BigphASE/delta2hap/src/tigrinc.cpp
src/BigphASE/delta2hap/src/translate.cpp