Metadata-Version: 2.1
Name: BigphASE
Version: 0.1.2
Summary: This package was devised to analyze hybrid RNA-seq using bi-parental graph strategy.
Home-page: https://github.com/yjiang296/BigphASE
Author: Yi Jiang, Yi Mu Ran , Zhule Liu
Author-email: jiangy296@mail2.sysu.edu.cn
License: GNU GPL v3.0 License
Platform: any
Classifier: Natural Language :: English
Classifier: Programming Language :: Python :: 3.12
License-File: LICENSE
